chima/__init__.py
chima/client.py
chima/core/__init__.py
chima/core/api_error.py
chima/core/datetime_utils.py
chima/core/jsonable_encoder.py
chima/core/remove_none_from_headers.py
chima/environment.py
chima/py.typed
chima/types/__init__.py
chima/types/ai_response_feedback_response.py
chima/types/conversation.py
chima/types/conversation_roles.py
chima/types/converse_response.py
chima/types/customer_context.py
chima/types/faq_response.py
chima/types/foundry_filter_response.py
chima/types/search_response.py
chima/types/user_query.py
chima-0.0.37.dist-info/METADATA
chima-0.0.37.dist-info/WHEEL
chima-0.0.37.dist-info/RECORD
